LICENSE
README.md
setup.cfg
setup.py
ip_pool/__about__.py
ip_pool/__init__.py
ip_pool/cli.py
ip_pool/ip_pool.py
ip_pool/version.py
ip_pool.egg-info/PKG-INFO
ip_pool.egg-info/SOURCES.txt
ip_pool.egg-info/dependency_links.txt
ip_pool.egg-info/entry_points.txt
ip_pool.egg-info/top_level.txt
ip_pool/config/default.yaml