Metadata-Version: 2.1
Name: ip-pool
Version: 0.1.0
Summary: Coming soon
Home-page: https://github.com/zcutlip/ip-address-pool
Author: Zachary Cutlip
Author-email: uid000@gmail.com
License: MIT
Platform: UNKNOWN
Requires-Python: >=3.7
License-File: LICENSE
